polars_sim-0.3.6.dist-info/METADATA
polars_sim-0.3.6.dist-info/WHEEL
polars_sim-0.3.6.dist-info/licenses/LICENSE.md
polars_sim/__init__.py
polars_sim/_polars_sim.pypy37-pp73-aarch64-linux-gnu.so
polars_sim/dataframe/__init__.py
polars_sim/dataframe/join.py
polars_sim-0.3.6.dist-info/RECORD
