Metadata-Version: 2.4
Name: polars_sim
Version: 0.3.6
Classifier: Programming Language :: Rust
Classifier: Programming Language :: Python :: Implementation :: CPython
Classifier: Programming Language :: Python :: Implementation :: PyPy
License-File: LICENSE.md
Summary: Fast similarity join for polars DataFrames.
Author-email: "Dr. André Schemaitat" <a.schemaitat@gmail.com>
Requires-Python: >=3.10, <3.14
